MANIFEST.in
README.txt
setup.cfg
setup.py
plonetheme/__init__.py
plonetheme.corporatemale.egg-info/PKG-INFO
plonetheme.corporatemale.egg-info/SOURCES.txt
plonetheme.corporatemale.egg-info/dependency_links.txt
plonetheme.corporatemale.egg-info/entry_points.txt
plonetheme.corporatemale.egg-info/namespace_packages.txt
plonetheme.corporatemale.egg-info/not-zip-safe
plonetheme.corporatemale.egg-info/paster_plugins.txt
plonetheme.corporatemale.egg-info/requires.txt
plonetheme.corporatemale.egg-info/top_level.txt
plonetheme/corporatemale/__init__.py
plonetheme/corporatemale/configure.zcml
plonetheme/corporatemale/profiles.zcml
plonetheme/corporatemale/setuphandlers.py
plonetheme/corporatemale/skins.zcml
plonetheme/corporatemale/tests.py
plonetheme/corporatemale/version.txt
plonetheme/corporatemale/Extensions/Install.py
plonetheme/corporatemale/browser/__init__.py
plonetheme/corporatemale/browser/configure.zcml
plonetheme/corporatemale/browser/interfaces.py
plonetheme/corporatemale/browser/viewlet.pt
plonetheme/corporatemale/browser/viewlets.py
plonetheme/corporatemale/browser/images/README.txt
plonetheme/corporatemale/browser/stylesheets/README.txt
plonetheme/corporatemale/browser/stylesheets/main.css
plonetheme/corporatemale/profiles/default/cssregistry.xml
plonetheme/corporatemale/profiles/default/import_steps.xml
plonetheme/corporatemale/profiles/default/jsregistry.xml
plonetheme/corporatemale/profiles/default/metadata.xml
plonetheme/corporatemale/profiles/default/plonetheme.corporatemale_various.txt
plonetheme/corporatemale/profiles/default/skins.xml
plonetheme/corporatemale/profiles/default/viewlets.xml
plonetheme/corporatemale/profiles/uninstall/skins.xml
plonetheme/corporatemale/profiles/uninstall/skins.xml~
plonetheme/corporatemale/profiles/uninstall/viewlets.xml
plonetheme/corporatemale/profiles/uninstall/viewlets.xml~
plonetheme/corporatemale/skins/plonetheme_corporatemale_custom_images/CONTENT.txt
plonetheme/corporatemale/skins/plonetheme_corporatemale_custom_images/masthead.png
plonetheme/corporatemale/skins/plonetheme_corporatemale_custom_templates/CONTENT.txt
plonetheme/corporatemale/skins/plonetheme_corporatemale_custom_templates/main_template.pt
plonetheme/corporatemale/skins/plonetheme_corporatemale_styles/CONTENT.txt
plonetheme/corporatemale/skins/plonetheme_corporatemale_styles/base_properties.props
plonetheme/corporatemale/skins/plonetheme_corporatemale_styles/color.css
