Metadata-Version: 1.0
Name: plonetheme.corporatemale
Version: 1.0dev
Summary: An elastic layout presentation suitable for a corporate business.
Home-page: http://svn.plone.org/svn/collective/plonethme.corporatemale
Author: Daniel Kvaternik
Author-email: dkvaternik@nngov.com
License: GPL
Keywords: web zope plone theme
Platform: UNKNOWN
Classifier: Framework :: Plone
Classifier: Programming Language :: Python
Classifier: Topic :: Software Development :: Libraries :: Python Modules
